domru_client/__init__.py
domru_client/client.py
domru_client/exceptions.py
domru_client/types.py
domru_client/utils.py
domru_client-1.0.10.dist-info/licenses/LICENSE
examples/ full_works.py
examples/auth.py
examples/old.py
examples/test.py
domru_client-1.0.10.dist-info/METADATA
domru_client-1.0.10.dist-info/WHEEL
domru_client-1.0.10.dist-info/top_level.txt
domru_client-1.0.10.dist-info/RECORD
