Metadata-Version: 2.4
Name: domru_client
Version: 1.0.10
Summary: Execute API calls to DomRU Internet provider from python code
Author-email: Erilov Nikita <minitwiks@gmail.com>
License: MIT
Project-URL: homepage, https://github.com/ErilovNikita/domru-client
Requires-Python: >=3.11
License-File: LICENSE
Requires-Dist: requests>=2.32.5
Requires-Dist: urllib3>=2.2.3
Requires-Dist: pydantic>=2.11.9
Provides-Extra: dev
Requires-Dist: dotenv==0.9.9; extra == "dev"
Requires-Dist: pytest==8.4.2; extra == "dev"
Requires-Dist: pytest-asyncio==1.2.0; extra == "dev"
Requires-Dist: pytest-cov==7.0.0; extra == "dev"
Requires-Dist: requests-mock==1.12.1; extra == "dev"
Dynamic: license-file
